README.md
setup.py
ckpt2tfserving/__init__.py
ckpt2tfserving/convertor.py
ckpt2tfserving/tfsession_patch.py
ckpt2tfserving.egg-info/PKG-INFO
ckpt2tfserving.egg-info/SOURCES.txt
ckpt2tfserving.egg-info/dependency_links.txt
ckpt2tfserving.egg-info/entry_points.txt
ckpt2tfserving.egg-info/not-zip-safe
ckpt2tfserving.egg-info/requires.txt
ckpt2tfserving.egg-info/top_level.txt
tests/__init__.py
tools/__init__.py
tools/ckpt_to_tfserving.py