Metadata-Version: 1.0
Name: ckpt2tfserving
Version: 1.0.4
Summary: a simple tool which can convert tensorflow checkpoint model file to tensorflow serving format.
Home-page: UNKNOWN
Author: Andy Cheung
Author-email: im@andy-cheung.me
License: MIT License
Keywords: tensorflow serving,checkpoint model
Platform: any
